README.md
setup.py
distons/__init__.py
distons/client.py
distons/component.py
distons/const.py
distons/dpy_overrides.py
distons/http.py
distons/interaction.py
distons/utils.py
distons.egg-info/PKG-INFO
distons.egg-info/SOURCES.txt
distons.egg-info/dependency_links.txt
distons.egg-info/requires.txt
distons.egg-info/top_level.txt
distons/ext/filters.py